{
    "numlags": 400,
    "results": [
        {
            "order": [
                1,
                0,
                1
            ],
            "rmse": 0.003319248740310611
        },
        {
            "order": [
                6,
                0,
                1
            ],
            "rmse": 0.0038667508673964797
        },
        {
            "order": [
                2,
                2,
                0
            ],
            "rmse": 0.008890291520674264
        },
        {
            "order": [
                3,
                2,
                2
            ],
            "rmse": 0.005502291696968971
        },
        {
            "order": [
                6,
                2,
                1
            ],
            "rmse": 0.005517448999539936
        },
        {
            "order": [
                6,
                2,
                0
            ],
            "rmse": 0.005752885549435861
        },
        {
            "order": [
                3,
                1,
                2
            ],
            "rmse": 0.004837648144843171
        },
        {
            "order": [
                2,
                1,
                0
            ],
            "rmse": 0.005076296519075027
        },
        {
            "order": [
                3,
                2,
                0
            ],
            "rmse": 0.0051167419729655
        },
        {
            "order": [
                6,
                0,
                0
            ],
            "rmse": 0.004485104970912163
        },
        {
            "order": [
                0,
                2,
                2
            ],
            "rmse": 0.004486152028928994
        },
        {
            "order": [
                1,
                2,
                0
            ],
            "rmse": 0.008111357392015654
        },
        {
            "order": [
                1,
                1,
                1
            ],
            "rmse": 0.005081758955456525
        },
        {
            "order": [
                3,
                1,
                1
            ],
            "rmse": 0.0053047340732167375
        },
        {
            "order": [
                2,
                1,
                1
            ],
            "rmse": 0.005319693023372113
        },
        {
            "order": [
                2,
                0,
                1
            ],
            "rmse": 0.004401276568178546
        },
        {
            "order": [
                0,
                1,
                1
            ],
            "rmse": 0.005289959338708305
        },
        {
            "order": [
                0,
                0,
                0
            ],
            "rmse": 0.004401452409035665
        },
        {
            "order": [
                3,
                0,
                1
            ],
            "rmse": 0.004507397532875618
        },
        {
            "order": [
                1,
                2,
                1
            ],
            "rmse": 0.005610867171263032
        }
    ],
    "stream": "finance-futures-oats-log-return.json",
    "todo": [
        [
            0,
            0,
            1
        ],
        [
            0,
            0,
            2
        ],
        [
            0,
            1,
            0
        ],
        [
            0,
            1,
            2
        ],
        [
            0,
            2,
            0
        ],
        [
            0,
            2,
            1
        ],
        [
            1,
            0,
            0
        ],
        [
            1,
            0,
            2
        ],
        [
            1,
            1,
            0
        ],
        [
            1,
            1,
            2
        ],
        [
            1,
            2,
            2
        ],
        [
            2,
            0,
            0
        ],
        [
            2,
            0,
            2
        ],
        [
            2,
            1,
            2
        ],
        [
            2,
            2,
            1
        ],
        [
            2,
            2,
            2
        ],
        [
            3,
            0,
            0
        ],
        [
            3,
            0,
            2
        ],
        [
            3,
            1,
            0
        ],
        [
            3,
            2,
            1
        ],
        [
            6,
            0,
            2
        ],
        [
            6,
            1,
            0
        ],
        [
            6,
            1,
            1
        ],
        [
            6,
            1,
            2
        ],
        [
            6,
            2,
            2
        ]
    ],
    "version": "0.1"
}