{
    "numlags": 400,
    "results": [
        {
            "order": [
                1,
                0,
                1
            ],
            "rmse": 0.00034679337246769717
        },
        {
            "order": [
                1,
                0,
                2
            ],
            "rmse": 0.00035181043492863904
        },
        {
            "order": [
                3,
                1,
                0
            ],
            "rmse": 0.00039643615757982957
        },
        {
            "order": [
                1,
                1,
                2
            ],
            "rmse": 0.00033836922925896905
        },
        {
            "order": [
                6,
                1,
                0
            ],
            "rmse": 0.0003467235255528358
        },
        {
            "order": [
                0,
                2,
                2
            ],
            "rmse": 0.0015525867339459265
        },
        {
            "order": [
                1,
                1,
                1
            ],
            "rmse": 0.00036609014922013095
        },
        {
            "order": [
                0,
                1,
                2
            ],
            "rmse": 0.00036312408926281306
        },
        {
            "order": [
                0,
                2,
                0
            ],
            "rmse": 0.00040736339168587877
        },
        {
            "order": [
                2,
                0,
                2
            ],
            "rmse": 0.00036258404134466976
        },
        {
            "order": [
                6,
                0,
                1
            ],
            "rmse": 0.0003631093064770161
        },
        {
            "order": [
                3,
                1,
                1
            ],
            "rmse": 0.0003639678797859142
        },
        {
            "order": [
                3,
                2,
                0
            ],
            "rmse": 0.00039901173110783953
        },
        {
            "order": [
                6,
                2,
                2
            ],
            "rmse": 0.0008640809444866361
        },
        {
            "order": [
                3,
                2,
                2
            ],
            "rmse": 0.0017512221784789714
        },
        {
            "order": [
                0,
                0,
                1
            ],
            "rmse": 0.00039810431747800654
        },
        {
            "order": [
                1,
                1,
                0
            ],
            "rmse": 0.0008576194570712865
        },
        {
            "order": [
                1,
                2,
                1
            ],
            "rmse": 0.0012116062606511702
        },
        {
            "order": [
                0,
                0,
                2
            ],
            "rmse": 0.00027798974675518256
        },
        {
            "order": [
                2,
                1,
                1
            ],
            "rmse": 0.000280019479280678
        },
        {
            "order": [
                2,
                2,
                2
            ],
            "rmse": 0.00030422594520275264
        },
        {
            "order": [
                3,
                2,
                1
            ],
            "rmse": 0.0002843620580851369
        },
        {
            "order": [
                1,
                2,
                0
            ],
            "rmse": 0.0003536543345804924
        },
        {
            "order": [
                2,
                2,
                0
            ],
            "rmse": 0.00035797313561367067
        },
        {
            "order": [
                3,
                0,
                2
            ],
            "rmse": 0.00027776908255349375
        },
        {
            "order": [
                1,
                0,
                0
            ],
            "rmse": 0.0002779483767941068
        },
        {
            "order": [
                2,
                1,
                0
            ],
            "rmse": 0.0002804719401685149
        },
        {
            "order": [
                0,
                2,
                1
            ],
            "rmse": 0.0009849719535238223
        },
        {
            "order": [
                6,
                0,
                0
            ],
            "rmse": 0.0003052412726544369
        }
    ],
    "stream": "finance-futures-30_year_bond-log-return.json",
    "todo": [
        [
            0,
            0,
            0
        ],
        [
            0,
            1,
            0
        ],
        [
            0,
            1,
            1
        ],
        [
            1,
            2,
            2
        ],
        [
            2,
            0,
            0
        ],
        [
            2,
            0,
            1
        ],
        [
            2,
            1,
            2
        ],
        [
            2,
            2,
            1
        ],
        [
            3,
            0,
            0
        ],
        [
            3,
            0,
            1
        ],
        [
            3,
            1,
            2
        ],
        [
            6,
            0,
            2
        ],
        [
            6,
            1,
            1
        ],
        [
            6,
            1,
            2
        ],
        [
            6,
            2,
            0
        ],
        [
            6,
            2,
            1
        ]
    ],
    "version": "0.1"
}