{
    "numlags": 400,
    "results": [
        {
            "order": [
                1,
                1,
                1
            ],
            "rmse": 51.28031965307842
        },
        {
            "order": [
                1,
                1,
                2
            ],
            "rmse": 51.342185372022534
        },
        {
            "order": [
                1,
                2,
                0
            ],
            "rmse": 51.38248556798849
        },
        {
            "order": [
                1,
                0,
                2
            ],
            "rmse": 52.068585160454056
        },
        {
            "order": [
                2,
                0,
                0
            ],
            "rmse": 52.08590449353739
        },
        {
            "order": [
                0,
                1,
                2
            ],
            "rmse": 53.40714057310615
        },
        {
            "order": [
                6,
                0,
                2
            ],
            "rmse": 384.0348973554026
        },
        {
            "order": [
                3,
                1,
                1
            ],
            "rmse": 464.45049420804844
        },
        {
            "order": [
                2,
                2,
                0
            ],
            "rmse": 948.6322318856144
        },
        {
            "order": [
                6,
                1,
                2
            ],
            "rmse": 834.3332718351089
        },
        {
            "order": [
                3,
                0,
                0
            ],
            "rmse": 892.5863426401562
        },
        {
            "order": [
                3,
                0,
                0
            ],
            "rmse": 892.5863426401562
        },
        {
            "order": [
                2,
                1,
                2
            ],
            "rmse": 416.12660038377146
        },
        {
            "order": [
                2,
                1,
                1
            ],
            "rmse": 416.2147603094648
        },
        {
            "order": [
                0,
                1,
                1
            ],
            "rmse": 1863.7628518232025
        },
        {
            "order": [
                2,
                2,
                1
            ],
            "rmse": 1871.0038583199057
        },
        {
            "order": [
                3,
                2,
                2
            ],
            "rmse": 1871.7458293114237
        },
        {
            "order": [
                6,
                2,
                2
            ],
            "rmse": 2713.6870878630084
        },
        {
            "order": [
                2,
                2,
                2
            ],
            "rmse": 2882.7179943407014
        },
        {
            "order": [
                2,
                2,
                2
            ],
            "rmse": 2882.7179943407014
        },
        {
            "order": [
                0,
                2,
                2
            ],
            "rmse": 3115.581813405037
        },
        {
            "order": [
                3,
                2,
                1
            ],
            "rmse": 1668.0990064477844
        },
        {
            "order": [
                0,
                0,
                2
            ],
            "rmse": 289.45456211948124
        }
    ],
    "stream": "finance-futures-russell_2000-volume.json",
    "todo": [
        [
            0,
            0,
            0
        ],
        [
            0,
            0,
            1
        ],
        [
            0,
            1,
            0
        ],
        [
            0,
            2,
            0
        ],
        [
            0,
            2,
            1
        ],
        [
            1,
            0,
            0
        ],
        [
            1,
            0,
            1
        ],
        [
            1,
            1,
            0
        ],
        [
            1,
            2,
            1
        ],
        [
            1,
            2,
            2
        ],
        [
            2,
            0,
            1
        ],
        [
            2,
            0,
            2
        ],
        [
            2,
            1,
            0
        ],
        [
            3,
            0,
            1
        ],
        [
            3,
            0,
            2
        ],
        [
            3,
            1,
            0
        ],
        [
            3,
            1,
            2
        ],
        [
            3,
            2,
            0
        ],
        [
            6,
            0,
            0
        ],
        [
            6,
            0,
            1
        ],
        [
            6,
            1,
            0
        ],
        [
            6,
            1,
            1
        ],
        [
            6,
            2,
            0
        ],
        [
            6,
            2,
            1
        ]
    ],
    "version": "0.1"
}