{
    "numlags": 400,
    "results": [
        {
            "mean": 0.0500913285698439,
            "order": [
                3,
                1,
                1
            ],
            "rmse": 0.9362618742646424,
            "tstamp": 1640060389.8062682
        },
        {
            "mean": 0.0500913285698439,
            "order": [
                1,
                0,
                1
            ],
            "rmse": 0.937199012984626,
            "tstamp": 1640060389.8062682
        },
        {
            "mean": 0.0500913285698439,
            "order": [
                6,
                0,
                0
            ],
            "rmse": 0.9390616229580092,
            "tstamp": 1640060389.8062682
        },
        {
            "mean": 0.05250243638688224,
            "order": [
                5,
                1,
                3
            ],
            "rmse": 0.9634468357528411,
            "tstamp": 1640063466.038831
        },
        {
            "mean": 0.05250243638688224,
            "order": [
                2,
                1,
                3
            ],
            "rmse": 0.9673023525967325,
            "tstamp": 1640063466.038831
        },
        {
            "mean": 0.05250243638688224,
            "order": [
                1,
                3,
                3
            ],
            "rmse": 1.1890663217189248,
            "tstamp": 1640063466.038831
        },
        {
            "mean": 0.0538848191195786,
            "order": [
                5,
                1,
                1
            ],
            "rmse": 0.9501658980452348,
            "tstamp": 1640064873.4360986
        },
        {
            "mean": 0.0538848191195786,
            "order": [
                4,
                0,
                3
            ],
            "rmse": 0.9514420703725505,
            "tstamp": 1640064873.4360986
        },
        {
            "mean": 0.0538848191195786,
            "order": [
                6,
                1,
                3
            ],
            "rmse": 0.963365249951517,
            "tstamp": 1640064873.4360986
        },
        {
            "mean": 0.05395985452166046,
            "order": [
                3,
                1,
                0
            ],
            "rmse": 0.8939573813395091,
            "tstamp": 1640114053.560083
        },
        {
            "mean": 0.05395985452166046,
            "order": [
                2,
                1,
                0
            ],
            "rmse": 0.9121662422089104,
            "tstamp": 1640114053.560083
        },
        {
            "mean": 0.05395985452166046,
            "order": [
                3,
                3,
                3
            ],
            "rmse": 0.9259399671979893,
            "tstamp": 1640114053.560083
        },
        {
            "mean": 0.054710463513000546,
            "order": [
                5,
                0,
                1
            ],
            "rmse": 0.9740851157761395,
            "tstamp": 1640141147.6416726
        },
        {
            "mean": 0.054710463513000546,
            "order": [
                3,
                3,
                0
            ],
            "rmse": 1.764592532097376,
            "tstamp": 1640141147.6416726
        },
        {
            "mean": 0.054710463513000546,
            "order": [
                0,
                3,
                1
            ],
            "rmse": 1.9669661095728976,
            "tstamp": 1640141147.6416726
        },
        {
            "mean": 0.055131005489343354,
            "order": [
                2,
                0,
                0
            ],
            "rmse": 0.9731383019198728,
            "tstamp": 1640142605.1124122
        },
        {
            "mean": 0.055131005489343354,
            "order": [
                3,
                0,
                3
            ],
            "rmse": 0.9792975083314609,
            "tstamp": 1640142605.1124122
        },
        {
            "mean": 0.055131005489343354,
            "order": [
                5,
                0,
                3
            ],
            "rmse": 0.9820662373846317,
            "tstamp": 1640142605.1124122
        },
        {
            "mean": 0.059313016872792036,
            "order": [
                3,
                0,
                0
            ],
            "rmse": 0.9620673259651313,
            "tstamp": 1640150077.247645
        },
        {
            "mean": 0.059313016872792036,
            "order": [
                5,
                0,
                0
            ],
            "rmse": 0.9668820245056197,
            "tstamp": 1640150077.247645
        },
        {
            "mean": 0.059313016872792036,
            "order": [
                6,
                3,
                0
            ],
            "rmse": 1.4276645902413068,
            "tstamp": 1640150077.247645
        },
        {
            "mean": 0.0608875141861284,
            "order": [
                0,
                0,
                3
            ],
            "rmse": 0.9692646837284556,
            "tstamp": 1640150442.757601
        },
        {
            "mean": 0.0608875141861284,
            "order": [
                0,
                1,
                1
            ],
            "rmse": 0.9986318130542028,
            "tstamp": 1640150442.757601
        },
        {
            "mean": 0.0608875141861284,
            "order": [
                2,
                3,
                0
            ],
            "rmse": 2.113108548426329,
            "tstamp": 1640150442.757601
        },
        {
            "mean": 0.0608875141861284,
            "order": [
                0,
                1,
                3
            ],
            "rmse": 0.9766448603554796,
            "tstamp": 1640151103.972617
        },
        {
            "mean": 0.0608875141861284,
            "order": [
                0,
                1,
                0
            ],
            "rmse": 1.201694714741225,
            "tstamp": 1640151103.972617
        },
        {
            "mean": 0.0608875141861284,
            "order": [
                1,
                3,
                0
            ],
            "rmse": 2.5835498894307967,
            "tstamp": 1640151103.972617
        },
        {
            "mean": 0.0626355337426091,
            "order": [
                6,
                1,
                1
            ],
            "rmse": 0.9514057575696421,
            "tstamp": 1640156388.216886
        },
        {
            "mean": 0.0626355337426091,
            "order": [
                2,
                1,
                1
            ],
            "rmse": 0.9563400117831143,
            "tstamp": 1640156388.216886
        },
        {
            "mean": 0.0626355337426091,
            "order": [
                0,
                3,
                3
            ],
            "rmse": 0.9952128720136673,
            "tstamp": 1640156388.216886
        },
        {
            "mean": 0.06313114805955912,
            "order": [
                2,
                3,
                1
            ],
            "rmse": 1.3274269834008627,
            "tstamp": 1640180501.2413337
        },
        {
            "mean": 0.05980975440361789,
            "order": [
                5,
                1,
                0
            ],
            "rmse": 0.9291128860627084,
            "tstamp": 1640208838.7078784
        },
        {
            "mean": 0.05980975440361789,
            "order": [
                4,
                3,
                3
            ],
            "rmse": 0.9604410409224744,
            "tstamp": 1640208838.7078784
        },
        {
            "mean": 0.05980975440361789,
            "order": [
                4,
                3,
                1
            ],
            "rmse": 1.1416405777132836,
            "tstamp": 1640208838.7078784
        },
        {
            "mean": 0.055698178885244254,
            "order": [
                2,
                0,
                1
            ],
            "rmse": 0.8818830594475673,
            "tstamp": 1640221379.4671516
        },
        {
            "mean": 0.055698178885244254,
            "order": [
                4,
                0,
                1
            ],
            "rmse": 0.8849792236923161,
            "tstamp": 1640221379.4671516
        },
        {
            "mean": 0.055698178885244254,
            "order": [
                4,
                1,
                0
            ],
            "rmse": 0.9372347553997082,
            "tstamp": 1640221379.4671516
        },
        {
            "mean": 0.057637433124858105,
            "order": [
                4,
                1,
                3
            ],
            "rmse": 0.9062385071951367,
            "tstamp": 1640232770.2609243
        },
        {
            "mean": 0.057637433124858105,
            "order": [
                6,
                1,
                0
            ],
            "rmse": 0.9580515618182028,
            "tstamp": 1640232770.2609243
        },
        {
            "mean": 0.057637433124858105,
            "order": [
                5,
                3,
                1
            ],
            "rmse": 1.1179127791189727,
            "tstamp": 1640232770.2609243
        }
    ],
    "stream": "z1~c5_solana~3555.json",
    "todo": [
        [
            0,
            0,
            0
        ],
        [
            0,
            0,
            1
        ],
        [
            0,
            3,
            0
        ],
        [
            1,
            0,
            0
        ],
        [
            1,
            0,
            3
        ],
        [
            1,
            1,
            0
        ],
        [
            1,
            1,
            1
        ],
        [
            1,
            1,
            3
        ],
        [
            1,
            3,
            1
        ],
        [
            2,
            0,
            3
        ],
        [
            2,
            3,
            3
        ],
        [
            3,
            0,
            1
        ],
        [
            3,
            1,
            3
        ],
        [
            3,
            3,
            1
        ],
        [
            4,
            0,
            0
        ],
        [
            4,
            1,
            1
        ],
        [
            4,
            3,
            0
        ],
        [
            5,
            3,
            0
        ],
        [
            5,
            3,
            3
        ],
        [
            6,
            0,
            1
        ],
        [
            6,
            0,
            3
        ],
        [
            6,
            3,
            1
        ],
        [
            6,
            3,
            3
        ]
    ],
    "version": "0.1"
}